auth_proxy_oidc/__init__.py
auth_proxy_oidc/plugin.py
auth_proxy_oidc-0.1.0.dist-info/METADATA
auth_proxy_oidc-0.1.0.dist-info/WHEEL
auth_proxy_oidc-0.1.0.dist-info/entry_points.txt
auth_proxy_oidc-0.1.0.dist-info/licenses/LICENSE
auth_proxy_oidc-0.1.0.dist-info/RECORD
