Metadata-Version: 2.4
Name: auth-proxy-oidc
Version: 0.1.0
Summary: OpenID Connect authentication plugin for auth-proxy
License-File: LICENSE
Requires-Python: >=3.8
Requires-Dist: authlib>=1.0.0
Requires-Dist: cryptography>=36.0.0
Requires-Dist: pyjwt[crypto]>=2.4.0
Requires-Dist: python-auth-proxy
Requires-Dist: redis>=4.2.0
Requires-Dist: requests
